[
    {
        "title": "A Broken Mother",
        "link": "https://www.fullhdfilmizlesene.live/film/a-broken-mother",
        "imdb": "5.2",
        "year": "2022",
        "image": "https://img.fullhdfilmizlesene.live/poster/film/a-broken-mother-63949.jpg"
    },
    {
        "title": "The Nannys Night",
        "link": "https://www.fullhdfilmizlesene.live/film/the-nannys-night",
        "imdb": "3.4",
        "year": "2021",
        "image": "https://img.fullhdfilmizlesene.live/poster/film/the-nannys-night-39893.jpg"
    },
    {
        "title": "Where the Scary Things Are",
        "link": "https://www.fullhdfilmizlesene.live/film/where-the-scary-things-are",
        "imdb": "3.0",
        "year": "2022",
        "image": "https://img.fullhdfilmizlesene.live/poster/film/where-the-scary-things-are-10699.jpg"
    },
    {
        "title": "I Won't Let You Go",
        "link": "https://www.fullhdfilmizlesene.live/film/i-won-t-let-you-go",
        "imdb": "5.3",
        "year": "2022",
        "image": "https://img.fullhdfilmizlesene.live/poster/film/i-won-t-let-you-go-28927.jpg"
    },
    {
        "title": "Mutlu Canavar Ailesi 2",
        "link": "https://www.fullhdfilmizlesene.live/film/mutlu-canavar-ailesi-2",
        "imdb": "4.9",
        "year": "2021",
        "image": "https://img.fullhdfilmizlesene.live/poster/film/mutlu-canavar-ailesi-2-monster-family-2-67193.jpg"
    },
    {
        "title": "Kaptan Sabertooth ve Minik Korsanlar Kayıp Elmas Peşinde",
        "link": "https://www.fullhdfilmizlesene.live/film/kaptan-sabertooth-ve-minik-korsanlar-kayip-elmas-pesinde",
        "imdb": "5.8",
        "year": "2019",
        "image": "https://img.fullhdfilmizlesene.live/poster/film/kaptan-sabertooth-ve-minik-korsanlar-kayip-elmas-pesinde-kaptein-sabeltann-og-den-magiske-diamant-1152.jpg"
    },
    {
        "title": "İlk Aşk",
        "link": "https://www.fullhdfilmizlesene.live/film/ilk-ask-2",
        "imdb": "6.7",
        "year": "2019",
        "image": "https://img.fullhdfilmizlesene.live/poster/film/ilk-ask-hatsukoi-53176.jpg"
    },
    {
        "title": "Moonshot",
        "link": "https://www.fullhdfilmizlesene.live/film/moonshot",
        "imdb": "5.6",
        "year": "2022",
        "image": "https://img.fullhdfilmizlesene.live/poster/film/moonshot-56109.jpg"
    },
    {
        "title": "Kod 355",
        "link": "https://www.fullhdfilmizlesene.live/film/kod-355",
        "imdb": "5.6",
        "year": "2022",
        "image": "https://img.fullhdfilmizlesene.live/poster/film/the-355-68366.jpg"
    },
    {
        "title": "Kod Adı: Sosisli",
        "link": "https://www.fullhdfilmizlesene.live/film/kod-adi-sosisli",
        "imdb": "4.1",
        "year": "2018",
        "image": "https://img.fullhdfilmizlesene.live/poster/film/fullhd-kod-adi-sosisli-hot-dog.jpg"
    },
    {
        "title": "Her şey mümkün",
        "link": "https://www.fullhdfilmizlesene.live/film/her-sey-mumkun",
        "imdb": "5.7",
        "year": "2022",
        "image": "https://img.fullhdfilmizlesene.live/poster/film/her-sey-mumkun-anything-s-possible-81036.jpg"
    },
    {
        "title": "Prey",
        "link": "https://www.fullhdfilmizlesene.live/film/prey-2",
        "imdb": "7.1",
        "year": "2022",
        "image": "https://img.fullhdfilmizlesene.live/poster/film/prey-2-20726.jpg"
    },
    {
        "title": "Zombiler 3",
        "link": "https://www.fullhdfilmizlesene.live/film/zombiler-3",
        "imdb": "5.4",
        "year": "2022",
        "image": "https://img.fullhdfilmizlesene.live/poster/film/zombiler-3-zombies-3-12352.jpg"
    },
    {
        "title": "Zombiler 2",
        "link": "https://www.fullhdfilmizlesene.live/film/zombiler-2",
        "imdb": "5.7",
        "year": "2020",
        "image": "https://img.fullhdfilmizlesene.live/poster/film/zombiler-2-z-o-m-b-i-e-s-2-51844.jpg"
    },
    {
        "title": "Zombiler",
        "link": "https://www.fullhdfilmizlesene.live/film/zombiler",
        "imdb": "6.0",
        "year": "2018",
        "image": "https://img.fullhdfilmizlesene.live/poster/film/zombiler-z-o-m-b-i-e-s-68167.jpg"
    },
    {
        "title": "Love li",
        "link": "https://www.fullhdfilmizlesene.live/film/love-li",
        "imdb": "9.5",
        "year": "2024",
        "image": "https://img.fullhdfilmizlesene.live/poster/film/love-li-3-32849.jpg"
    },
    {
        "title": "Munjya",
        "link": "https://www.fullhdfilmizlesene.live/film/munjya",
        "imdb": "7.2",
        "year": "2024",
        "image": "https://img.fullhdfilmizlesene.live/poster/film/munjya-91431.jpg"
    },
    {
        "title": "Menudas piezas",
        "link": "https://www.fullhdfilmizlesene.live/film/menudas-piezas",
        "imdb": "5.9",
        "year": "2024",
        "image": "https://img.fullhdfilmizlesene.live/poster/film/menudas-piezas-77667.jpg"
    }
]