[
    {
        "title": "The Infinity Project",
        "link": "https://www.fullhdfilmizlesene.live/film/the-infinity-project",
        "imdb": "4.8",
        "year": "2018",
        "image": "https://img.fullhdfilmizlesene.live/poster/film/fullhd-the-infinity-project.jpg"
    },
    {
        "title": "Dolceroma",
        "link": "https://www.fullhdfilmizlesene.live/film/dolceroma",
        "imdb": "5.7",
        "year": "2019",
        "image": "https://img.fullhdfilmizlesene.live/poster/film/fullhd-dolceroma.jpg"
    },
    {
        "title": "Kurier",
        "link": "https://www.fullhdfilmizlesene.live/film/kurier",
        "imdb": "5.9",
        "year": "2019",
        "image": "https://img.fullhdfilmizlesene.live/poster/film/fullhd-kurier.jpg"
    },
    {
        "title": "Yemin",
        "link": "https://www.fullhdfilmizlesene.live/film/yemin-2",
        "imdb": "5.6",
        "year": "2018",
        "image": "https://img.fullhdfilmizlesene.live/poster/film/fullhd-yemin-the-oath-2.jpg"
    },
    {
        "title": "Sürükleniş",
        "link": "https://www.fullhdfilmizlesene.live/film/suruklenis",
        "imdb": "6.6",
        "year": "2018",
        "image": "https://img.fullhdfilmizlesene.live/poster/film/fullhd-suruklenis-adrift.jpg"
    },
    {
        "title": "Ringde Bir Aile",
        "link": "https://www.fullhdfilmizlesene.live/film/ringde-bir-aile",
        "imdb": "7.1",
        "year": "2019",
        "image": "https://img.fullhdfilmizlesene.live/poster/film/fullhd-fighting-with-my-family-izle.jpg"
    },
    {
        "title": "Mahluklar 5",
        "link": "https://www.fullhdfilmizlesene.live/film/mahluklar-5",
        "imdb": "3.7",
        "year": "2019",
        "image": "https://img.fullhdfilmizlesene.live/poster/film/fullhd-mahluklar-5-critters-attack-critters-5.jpg"
    },
    {
        "title": "The Chain",
        "link": "https://www.fullhdfilmizlesene.live/film/the-chain",
        "imdb": "4.3",
        "year": "2019",
        "image": "https://img.fullhdfilmizlesene.live/poster/film/fullhd-the-chain.jpg"
    },
    {
        "title": "Assassinaut",
        "link": "https://www.fullhdfilmizlesene.live/film/assassinaut",
        "imdb": "4.0",
        "year": "2019",
        "image": "https://img.fullhdfilmizlesene.live/poster/film/fullhd-assassinaut.jpg"
    },
    {
        "title": "Palyaço Motel",
        "link": "https://www.fullhdfilmizlesene.live/film/palyaco-motel",
        "imdb": "2.9",
        "year": "2019",
        "image": "https://img.fullhdfilmizlesene.live/poster/film/fullhd-clown-motel-spirits-arise.jpg"
    },
    {
        "title": "İstila Altında",
        "link": "https://www.fullhdfilmizlesene.live/film/istila-altinda",
        "imdb": "6.0",
        "year": "2019",
        "image": "https://img.fullhdfilmizlesene.live/poster/film/fullhd-captive-state-2019-film-izle.jpg"
    },
    {
        "title": "Rock Paper Dead",
        "link": "https://www.fullhdfilmizlesene.live/film/rock-paper-dead",
        "imdb": "4.2",
        "year": "2017",
        "image": "https://img.fullhdfilmizlesene.live/poster/film/fullhd-rock-paper-dead.jpg"
    },
    {
        "title": "Otherhood",
        "link": "https://www.fullhdfilmizlesene.live/film/otherhood",
        "imdb": "6.1",
        "year": "2019",
        "image": "https://img.fullhdfilmizlesene.live/poster/film/fullhd-otherhood.jpg"
    },
    {
        "title": "Kıskanç",
        "link": "https://www.fullhdfilmizlesene.live/film/kiskanc",
        "imdb": "6.1",
        "year": "2017",
        "image": "https://img.fullhdfilmizlesene.live/poster/film/fullhd-kiskanc-jalouse.jpg"
    },
    {
        "title": "Seninle Başım Dertte",
        "link": "https://www.fullhdfilmizlesene.live/film/seninle-basim-dertte",
        "imdb": "6.2",
        "year": "2018",
        "image": "https://img.fullhdfilmizlesene.live/poster/film/fullhd-seninle-basim-dertte-the-trouble-with-you-en-liberte.jpg"
    },
    {
        "title": "Kursk",
        "link": "https://www.fullhdfilmizlesene.live/film/kursk",
        "imdb": "6.6",
        "year": "2018",
        "image": "https://img.fullhdfilmizlesene.live/poster/film/fullhd-kursk.jpg"
    },
    {
        "title": "Üst Düzey Yaşam",
        "link": "https://www.fullhdfilmizlesene.live/film/ust-duzey-yasam",
        "imdb": "5.8",
        "year": "2018",
        "image": "https://img.fullhdfilmizlesene.live/poster/film/fullhd-ust-duzey-yasam-high-life.jpg"
    },
    {
        "title": "Finding Steve McQueen",
        "link": "https://www.fullhdfilmizlesene.live/film/finding-steve-mcqueen",
        "imdb": "6.2",
        "year": "2019",
        "image": "https://img.fullhdfilmizlesene.live/poster/film/fullhd-finding-steve-mcqueen.jpg"
    }
]