[
    {
        "title": "Perde Arkası: Hope Solo'nun Futbol Kariyeri",
        "link": "https://www.fullhdfilmizlesene.live/film/perde-arkasi-hope-solo-nun-futbol-kariyeri",
        "rapid_link": "",
        "imdb": "7.2",
        "year": "2024",
        "image": "https://img.fullhdfilmizlesene.live/poster/film/perde-arkasi-hope-solo-nun-futbol-kariyeri-untold-hope-solo-vs-us-soccer-10180.jpg"
    },
    {
        "title": "Ok Ucu",
        "link": "https://www.fullhdfilmizlesene.live/film/ok-ucu",
        "rapid_link": "",
        "imdb": "4.4",
        "year": "2016",
        "image": "https://img.fullhdfilmizlesene.live/poster/film/ok-ucu-arrowhead-5067.jpg"
    },
    {
        "title": "Sen Aydinlatirsin Geceyi",
        "link": "https://www.fullhdfilmizlesene.live/film/sen-aydinlatirsin-geceyi",
        "rapid_link": "",
        "imdb": "7.7",
        "year": "2013",
        "image": "https://img.fullhdfilmizlesene.live/poster/film/sen-aydinlatirsin-geceyi-64233.jpg"
    },
    {
        "title": "İhtiras Rüzgarları",
        "link": "https://www.fullhdfilmizlesene.live/film/ihtiras-ruzgarlari",
        "rapid_link": "",
        "imdb": "7.5",
        "year": "1994",
        "image": "https://img.fullhdfilmizlesene.live/poster/film/ihtiras-ruzgarlari-legends-of-the-fall-86583.jpg"
    },
    {
        "title": "Koruyucu",
        "link": "https://www.fullhdfilmizlesene.live/film/koruyucu-6",
        "rapid_link": "",
        "imdb": "6.5",
        "year": "2012",
        "image": "https://img.fullhdfilmizlesene.live/poster/film/koruyucu-safe-25969.jpg"
    },
    {
        "title": "Nerden Biliyorsun?",
        "link": "https://www.fullhdfilmizlesene.live/film/nerden-biliyorsun",
        "rapid_link": "",
        "imdb": "5.4",
        "year": "2010",
        "image": "https://img.fullhdfilmizlesene.live/poster/film/nerden-biliyorsun-how-do-you-know-3-57190.jpg"
    },
    {
        "title": "Gelin Benim Olacak",
        "link": "https://www.fullhdfilmizlesene.live/film/gelin-benim-olacak",
        "rapid_link": "",
        "imdb": "5.8",
        "year": "2008",
        "image": "https://img.fullhdfilmizlesene.live/poster/film/gelin-benim-olacak-made-of-honor-39246.jpg"
    },
    {
        "title": "Keskin Nişancı: Miras",
        "link": "https://www.fullhdfilmizlesene.live/film/keskin-nisanci-miras-2",
        "rapid_link": "",
        "imdb": "5.3",
        "year": "2014",
        "image": "https://img.fullhdfilmizlesene.live/poster/film/keskin-nisanci-miras-sniper-legacy-65706.jpg"
    },
    {
        "title": "Keskin Nişancı 3",
        "link": "https://www.fullhdfilmizlesene.live/film/keskin-nisanci-3",
        "rapid_link": "",
        "imdb": "5.2",
        "year": "2004",
        "image": "https://img.fullhdfilmizlesene.live/poster/film/keskin-nisanci-3-sniper-3-5764.jpg"
    },
    {
        "title": "Tetikçi 2",
        "link": "https://www.fullhdfilmizlesene.live/film/tetikci-2-2",
        "rapid_link": "",
        "imdb": "5.2",
        "year": "2002",
        "image": "https://img.fullhdfilmizlesene.live/poster/film/tetikci-2-sniper-2-20815.jpg"
    },
    {
        "title": "Tetikçi",
        "link": "https://www.fullhdfilmizlesene.live/film/tetikci-7",
        "rapid_link": "",
        "imdb": "6.1",
        "year": "1993",
        "image": "https://img.fullhdfilmizlesene.live/poster/film/tetikci-sniper-58816.jpg"
    },
    {
        "title": "Karateci Çocuk 4: Yeni Nesil",
        "link": "https://www.fullhdfilmizlesene.live/film/karateci-cocuk-4-yeni-nesil",
        "rapid_link": "",
        "imdb": "4.6",
        "year": "1994",
        "image": "https://img.fullhdfilmizlesene.live/poster/film/karateci-cocuk-4-yeni-nesil-the-next-karate-kid-15784.jpg"
    },
    {
        "title": "Karateci Çocuk 3",
        "link": "https://www.fullhdfilmizlesene.live/film/karateci-cocuk-3",
        "rapid_link": "",
        "imdb": "5.3",
        "year": "1989",
        "image": "https://img.fullhdfilmizlesene.live/poster/film/karateci-cocuk-3-karate-kid-3-78782.jpg"
    },
    {
        "title": "Karateci Çocuk 2",
        "link": "https://www.fullhdfilmizlesene.live/film/karateci-cocuk-2",
        "rapid_link": "",
        "imdb": "6.1",
        "year": "1986",
        "image": "https://img.fullhdfilmizlesene.live/poster/film/karateci-cocuk-2-the-karate-kid-part-2-2102.jpg"
    },
    {
        "title": "Karateci Çocuk",
        "link": "https://www.fullhdfilmizlesene.live/film/karateci-cocuk",
        "rapid_link": "",
        "imdb": "7.3",
        "year": "1984",
        "image": "https://img.fullhdfilmizlesene.live/poster/film/karateci-cocuk-the-karate-kid-43855.jpg"
    },
    {
        "title": "Keskin Nişancı 7",
        "link": "https://www.fullhdfilmizlesene.live/film/keskin-nisanci-7",
        "rapid_link": "",
        "imdb": "5.6",
        "year": "2017",
        "image": "https://img.fullhdfilmizlesene.live/poster/film/keskin-nisanci-sniper-ultimate-kill-55421.jpg"
    },
    {
        "title": "Yasak dans",
        "link": "https://www.fullhdfilmizlesene.live/film/yasak-dans",
        "rapid_link": "",
        "imdb": "6.6",
        "year": "1984",
        "image": "https://img.fullhdfilmizlesene.live/poster/film/yasak-dans-footloose-73948.jpg"
    },
    {
        "title": "Başka Bir Yerde",
        "link": "https://www.fullhdfilmizlesene.live/film/baska-bir-yerde-3",
        "rapid_link": "",
        "imdb": "6.3",
        "year": "2010",
        "image": "https://img.fullhdfilmizlesene.live/poster/film/baska-bir-yerde-somewhere-36333.jpg"
    }
]