[
    {
        "title": "The Trial",
        "link": "https://www.fullhdfilmizlesene.live/film/the-trial-2",
        "imdb": "5.9",
        "year": "2025",
        "image": "https://img.fullhdfilmizlesene.live/poster/film/the-trial-2-77903.jpg",
        "rapid_link": "https://rapidvid.net/vod/v1x938f3588"
    },
    {
        "title": "The Other",
        "link": "https://www.fullhdfilmizlesene.live/film/the-other",
        "imdb": "4.6",
        "year": "2025",
        "image": "https://img.fullhdfilmizlesene.live/poster/film/the-other-4-90928.jpg",
        "rapid_link": "https://rapidvid.net/vod/v1x09f8524d"
    },
    {
        "title": "Sovereign",
        "link": "https://www.fullhdfilmizlesene.live/film/sovereign",
        "imdb": "6.4",
        "year": "2025",
        "image": "https://img.fullhdfilmizlesene.live/poster/film/sovereign-57685.jpg",
        "rapid_link": "https://rapidvid.net/vod/v1x845c9164"
    },
    {
        "title": "Reloaded 3",
        "link": "https://www.fullhdfilmizlesene.live/film/reloaded-3",
        "imdb": "5.1",
        "year": "2025",
        "image": "https://img.fullhdfilmizlesene.live/poster/film/reloaded-3-42703.jpg",
        "rapid_link": "https://rapidvid.net/vod/v1x5a15d769"
    },
    {
        "title": "Knee High",
        "link": "https://www.fullhdfilmizlesene.live/film/knee-high",
        "imdb": "5.8",
        "year": "2025",
        "image": "https://img.fullhdfilmizlesene.live/poster/film/knee-high-61316.jpg",
        "rapid_link": "https://rapidvid.net/vod/v1x0d387ccc"
    },
    {
        "title": "Killing the Competition",
        "link": "https://www.fullhdfilmizlesene.live/film/killing-the-competition",
        "imdb": "6.0",
        "year": "2025",
        "image": "https://img.fullhdfilmizlesene.live/poster/film/killing-the-competition-66822.jpg",
        "rapid_link": "https://rapidvid.net/vod/v1x9b495aab"
    },
    {
        "title": "Everything's Going to Be Great",
        "link": "https://www.fullhdfilmizlesene.live/film/everything-s-going-to-be-great",
        "imdb": "5.6",
        "year": "2025",
        "image": "https://img.fullhdfilmizlesene.live/poster/film/everything-s-going-to-be-great-66952.jpg",
        "rapid_link": "https://rapidvid.net/vod/v1xd797be3a"
    },
    {
        "title": "Rainbow World: The Movie",
        "link": "https://www.fullhdfilmizlesene.live/film/rainbow-world-the-movie",
        "imdb": "6.8",
        "year": "2024",
        "image": "https://img.fullhdfilmizlesene.live/poster/film/rainbow-world-the-movie-50556.jpg",
        "rapid_link": "https://rapidvid.net/vod/v1x864fbfac"
    },
    {
        "title": "Deadly Escape",
        "link": "https://www.fullhdfilmizlesene.live/film/deadly-escape",
        "imdb": "4.9",
        "year": "2025",
        "image": "https://img.fullhdfilmizlesene.live/poster/film/deadly-escape-93244.jpg",
        "rapid_link": "https://rapidvid.net/vod/v1x9476ef9b"
    },
    {
        "title": "Blood Pay",
        "link": "https://www.fullhdfilmizlesene.live/film/blood-pay-2",
        "imdb": "2.5",
        "year": "2025",
        "image": "https://img.fullhdfilmizlesene.live/poster/film/blood-pay-2-86207.jpg",
        "rapid_link": "https://rapidvid.net/vod/v1xcb6f6f86"
    },
    {
        "title": "A Scam Called Love",
        "link": "https://www.fullhdfilmizlesene.live/film/a-scam-called-love",
        "imdb": "4.9",
        "year": "2025",
        "image": "https://img.fullhdfilmizlesene.live/poster/film/a-scam-called-love-43552.jpg",
        "rapid_link": "https://rapidvid.net/vod/v1xda0ef3d8"
    },
    {
        "title": "100 dni do matury",
        "link": "https://www.fullhdfilmizlesene.live/film/100-dni-do-matury",
        "imdb": "4.6",
        "year": "2025",
        "image": "https://img.fullhdfilmizlesene.live/poster/film/100-dni-do-matury-34860.jpg",
        "rapid_link": "https://rapidvid.net/vod/v1x48ce2a21"
    },
    {
        "title": "Bir Skandalın Peşinde",
        "link": "https://www.fullhdfilmizlesene.live/film/bir-skandalin-pesinde-2",
        "imdb": "6.7",
        "year": "2023",
        "image": "https://img.fullhdfilmizlesene.live/poster/film/bir-skandalin-pesinde-may-december-42056.jpg",
        "rapid_link": "https://rapidvid.net/vod/v1x02f8d037"
    },
    {
        "title": "Hızlı ve Ateşli: Ölüm Yarışı",
        "link": "https://www.fullhdfilmizlesene.live/film/hizli-ve-atesli-olum-yarisi",
        "imdb": "2.3",
        "year": "2020",
        "image": "https://img.fullhdfilmizlesene.live/poster/film/fullhd-fast-and-fierce-death-race-izle.jpg",
        "rapid_link": "https://rapidvid.net/vod/v1xd71fb54d"
    },
    {
        "title": "Hızlı Ve Ateşli",
        "link": "https://www.fullhdfilmizlesene.live/film/hizli-ve-atesli",
        "imdb": "2.6",
        "year": "2017",
        "image": "https://img.fullhdfilmizlesene.live/poster/film/fullhd-hizli-ve-atesli-the-fast-and-the-fierce.jpg",
        "rapid_link": "https://rapidvid.net/vod/v1x5339aa3d"
    },
    {
        "title": "Maybe Forever",
        "link": "https://www.fullhdfilmizlesene.live/film/maybe-forever",
        "imdb": "6.0",
        "year": "2024",
        "image": "https://img.fullhdfilmizlesene.live/poster/film/maybe-forever-18413.jpg",
        "rapid_link": "https://rapidvid.net/vod/v1x9cc69d2b"
    },
    {
        "title": "OOP Saga Times Opposite Path",
        "link": "https://www.fullhdfilmizlesene.live/film/oop-saga-times-opposite-path",
        "imdb": "5.7",
        "year": "2025",
        "image": "https://img.fullhdfilmizlesene.live/poster/film/oop-saga-times-opposite-path-24704.jpg",
        "rapid_link": "https://rapidvid.net/vod/v1xa6a7d3ca"
    },
    {
        "title": "Noah's Arc: The Movie",
        "link": "https://www.fullhdfilmizlesene.live/film/noah-s-arc-the-movie",
        "imdb": "6.0",
        "year": "2025",
        "image": "https://img.fullhdfilmizlesene.live/poster/film/noah-s-arc-the-movie-83720.jpg",
        "rapid_link": "https://rapidvid.net/vod/v1xb7986d48"
    }
]