[
    {
        "title": "Talking to Ghosts",
        "link": "https://www.fullhdfilmizlesene.live/film/talking-to-ghosts",
        "imdb": "3.9",
        "year": "2023",
        "image": "https://img.fullhdfilmizlesene.live/poster/film/talking-to-ghosts-77938.jpg"
    },
    {
        "title": "Black Clover: Sword of the Wizard King",
        "link": "https://www.fullhdfilmizlesene.live/film/black-clover-sword-of-the-wizard-king",
        "imdb": "7.4",
        "year": "2023",
        "image": "https://img.fullhdfilmizlesene.live/poster/film/black-clover-sword-of-the-wizard-king-34003.jpg"
    },
    {
        "title": "Extraction 2",
        "link": "https://www.fullhdfilmizlesene.live/film/extraction-2-3",
        "imdb": "7.0",
        "year": "2023",
        "image": "https://img.fullhdfilmizlesene.live/poster/film/extraction-2-izle-3-52777.jpg"
    },
    {
        "title": "Extraction",
        "link": "https://www.fullhdfilmizlesene.live/film/extraction-2",
        "imdb": "6.8",
        "year": "2020",
        "image": "https://img.fullhdfilmizlesene.live/poster/film/extraction-izle-1-28792.jpg"
    },
    {
        "title": "Vasya ne v sebe",
        "link": "https://www.fullhdfilmizlesene.live/film/vasya-ne-v-sebe",
        "imdb": "6.0",
        "year": "2023",
        "image": "https://img.fullhdfilmizlesene.live/poster/film/vasya-ne-v-sebe-60523.jpg"
    },
    {
        "title": "The Vampire Next Door",
        "link": "https://www.fullhdfilmizlesene.live/film/the-vampire-next-door",
        "imdb": "4.6",
        "year": "2024",
        "image": "https://img.fullhdfilmizlesene.live/poster/film/the-vampire-next-door-51912.jpg"
    },
    {
        "title": "Ta'am al Tufah, Ahmar",
        "link": "https://www.fullhdfilmizlesene.live/film/ta-am-al-tufah-ahmar",
        "imdb": "5.9",
        "year": "2022",
        "image": "https://img.fullhdfilmizlesene.live/poster/film/ta-am-al-tufah-ahmar-70131.jpg"
    },
    {
        "title": "Out of Hand",
        "link": "https://www.fullhdfilmizlesene.live/film/out-of-hand",
        "imdb": "5.2",
        "year": "2023",
        "image": "https://img.fullhdfilmizlesene.live/poster/film/out-of-hand-97573.jpg"
    },
    {
        "title": "It Only Takes a Night",
        "link": "https://www.fullhdfilmizlesene.live/film/it-only-takes-a-night",
        "imdb": "6.0",
        "year": "2023",
        "image": "https://img.fullhdfilmizlesene.live/poster/film/it-only-takes-a-night-5940.jpg"
    },
    {
        "title": "Dashcam",
        "link": "https://www.fullhdfilmizlesene.live/film/dashcam-2",
        "imdb": "4.6",
        "year": "2021",
        "image": "https://img.fullhdfilmizlesene.live/poster/film/dashcam-2-21908.jpg"
    },
    {
        "title": "The Childe",
        "link": "https://www.fullhdfilmizlesene.live/film/the-childe",
        "imdb": "6.9",
        "year": "2023",
        "image": "https://img.fullhdfilmizlesene.live/poster/film/the-childe-58183.jpg"
    },
    {
        "title": "River Wild",
        "link": "https://www.fullhdfilmizlesene.live/film/river-wild",
        "imdb": "5.4",
        "year": "2023",
        "image": "https://img.fullhdfilmizlesene.live/poster/film/river-wild-51689.jpg"
    },
    {
        "title": "Carry on Jatta 3",
        "link": "https://www.fullhdfilmizlesene.live/film/carry-on-jatta-3",
        "imdb": "6.1",
        "year": "2023",
        "image": "https://img.fullhdfilmizlesene.live/poster/film/carry-on-jatta-3-34983.jpg"
    },
    {
        "title": "Cinnamon",
        "link": "https://www.fullhdfilmizlesene.live/film/cinnamon",
        "imdb": "6.6",
        "year": "2023",
        "image": "https://img.fullhdfilmizlesene.live/poster/film/cinnamon-13195.jpg"
    },
    {
        "title": "Spin the Block",
        "link": "https://www.fullhdfilmizlesene.live/film/spin-the-block",
        "imdb": "6.3",
        "year": "5.1",
        "image": "https://img.fullhdfilmizlesene.live/poster/film/spin-the-block-50135.jpg"
    },
    {
        "title": "Dante's Shadow of Sin",
        "link": "https://www.fullhdfilmizlesene.live/film/dante-s-shadow-of-sin",
        "imdb": "6.2",
        "year": "2021",
        "image": "https://img.fullhdfilmizlesene.live/poster/film/dante-s-shadow-of-sin-38201.jpg"
    },
    {
        "title": "A Killer Romance",
        "link": "https://www.fullhdfilmizlesene.live/film/a-killer-romance",
        "imdb": "6.5",
        "year": "2023",
        "image": "https://img.fullhdfilmizlesene.live/poster/film/a-killer-romance-50445.jpg"
    },
    {
        "title": "Christmas Bake-Off",
        "link": "https://www.fullhdfilmizlesene.live/film/christmas-bake-off",
        "imdb": "6.7",
        "year": "2023",
        "image": "https://img.fullhdfilmizlesene.live/poster/film/christmas-bake-off-15965.jpg"
    }
]