[
    {
        "title": "Troll: Kuyruklu Macera",
        "link": "https://www.fullhdfilmizlesene.live/film/troll-kuyruklu-macera",
        "imdb": "4.9",
        "year": "2018",
        "image": "https://img.fullhdfilmizlesene.live/poster/film/troll-kuyruklu-macera-troll-the-tale-of-a-tail-11015.jpg"
    },
    {
        "title": "DC Süper Evciller Takımı",
        "link": "https://www.fullhdfilmizlesene.live/film/dc-super-evciller-takimi",
        "imdb": "7.1",
        "year": "2022",
        "image": "https://img.fullhdfilmizlesene.live/poster/film/dc-super-evciller-takimi-dc-league-of-super-pets-83816.jpg"
    },
    {
        "title": "Düğünde Nefret Ettiğimiz İnsanlar",
        "link": "https://www.fullhdfilmizlesene.live/film/dugunde-nefret-ettigimiz-insanlar",
        "imdb": "5.8",
        "year": "2022",
        "image": "https://img.fullhdfilmizlesene.live/poster/film/dugunde-nefret-ettigimiz-insanlar-the-people-we-hate-at-the-wedding-33201.jpg"
    },
    {
        "title": "The Violence Action",
        "link": "https://www.fullhdfilmizlesene.live/film/the-violence-action",
        "imdb": "4.7",
        "year": "2022",
        "image": "https://img.fullhdfilmizlesene.live/poster/film/the-violence-action-12864.jpg"
    },
    {
        "title": "Hayaller Diyarı",
        "link": "https://www.fullhdfilmizlesene.live/film/hayaller-diyari",
        "imdb": "6.7",
        "year": "2022",
        "image": "https://img.fullhdfilmizlesene.live/poster/film/hayaller-diyari-slumberland-99831.jpg"
    },
    {
        "title": "Marian'ın Serüvenleri",
        "link": "https://www.fullhdfilmizlesene.live/film/marian-in-seruvenleri",
        "imdb": "3.4",
        "year": "2022",
        "image": "https://img.fullhdfilmizlesene.live/poster/film/the-adventures-of-maid-marian-17676.jpg"
    },
    {
        "title": "Brian Wilson: Vadedilen Uzun Yol",
        "link": "https://www.fullhdfilmizlesene.live/film/brian-wilson-vadedilen-uzun-yol",
        "imdb": "7.3",
        "year": "2021",
        "image": "https://img.fullhdfilmizlesene.live/poster/film/brian-wilson-vadedilen-uzun-yol-brian-wilson-long-promised-road-7621.jpg"
    },
    {
        "title": "Noel Günlüğü",
        "link": "https://www.fullhdfilmizlesene.live/film/noel-gunlugu",
        "imdb": "6.1",
        "year": "2022",
        "image": "https://img.fullhdfilmizlesene.live/poster/film/noel-gunlugu-the-noel-diary-56701.jpg"
    },
    {
        "title": "Not Okay",
        "link": "https://www.fullhdfilmizlesene.live/film/not-okay",
        "imdb": "6.1",
        "year": "2022",
        "image": "https://img.fullhdfilmizlesene.live/poster/film/not-okay-71128.jpg"
    },
    {
        "title": "Minyonlar 2: Gru'nun Yükselişi",
        "link": "https://www.fullhdfilmizlesene.live/film/minyonlar-2-gru-nun-yukselisi",
        "imdb": "6.5",
        "year": "2022",
        "image": "https://img.fullhdfilmizlesene.live/poster/film/minyonlar-2-gru-nun-yukselisi-minions-the-rise-of-gru-26100.jpg"
    },
    {
        "title": "Accident Man 2",
        "link": "https://www.fullhdfilmizlesene.live/film/accident-man-2",
        "imdb": "5.9",
        "year": "2022",
        "image": "https://img.fullhdfilmizlesene.live/poster/film/accident-man-2-52358.jpg"
    },
    {
        "title": "Kurt ve Aslan",
        "link": "https://www.fullhdfilmizlesene.live/film/kurt-ve-aslan",
        "imdb": "6.2",
        "year": "2021",
        "image": "https://img.fullhdfilmizlesene.live/poster/film/kurt-ve-aslan-70346.jpg"
    },
    {
        "title": "Geçmişi Olmayan Adam",
        "link": "https://www.fullhdfilmizlesene.live/film/gecmisi-olmayan-adam-2",
        "imdb": "7.8",
        "year": "2002",
        "image": "https://img.fullhdfilmizlesene.live/poster/film/gecmisi-olmayan-adam-the-bourne-identity-75935.jpg"
    },
    {
        "title": "Soğuk Rekabet",
        "link": "https://www.fullhdfilmizlesene.live/film/soguk-rekabet",
        "imdb": "6.2",
        "year": "2022",
        "image": "https://img.fullhdfilmizlesene.live/poster/film/soguk-rekabet-71371.jpg"
    },
    {
        "title": "Büyük İkramiye",
        "link": "https://www.fullhdfilmizlesene.live/film/buyuk-ikramiye-2",
        "imdb": "5.5",
        "year": "2022",
        "image": "https://img.fullhdfilmizlesene.live/poster/film/buyuk-ikramiye-lost-lotteries-24946.jpg"
    },
    {
        "title": "Gececi",
        "link": "https://www.fullhdfilmizlesene.live/film/gececi-2",
        "imdb": "6.2",
        "year": "2019",
        "image": "https://img.fullhdfilmizlesene.live/poster/film/gececi-nocturnal-93461.jpg"
    },
    {
        "title": "Matriarch",
        "link": "https://www.fullhdfilmizlesene.live/film/matriarch-2",
        "imdb": "4.6",
        "year": "2022",
        "image": "https://img.fullhdfilmizlesene.live/poster/film/matriarch-73135.jpg"
    },
    {
        "title": "Downton Abbey: Yeni Çağ",
        "link": "https://www.fullhdfilmizlesene.live/film/downton-abbey-yeni-cag",
        "imdb": "7.4",
        "year": "2022",
        "image": "https://img.fullhdfilmizlesene.live/poster/film/downton-abbey-yeni-cag-downton-abbey-a-new-era-78422.jpg"
    }
]