[
    {
        "title": "Geçmişin İzleri",
        "link": "https://www.fullhdfilmizlesene.live/film/gecmisin-izleri",
        "imdb": "3.8",
        "year": "2006",
        "image": "https://img.fullhdfilmizlesene.live/poster/film/gecmisin-izleri-filmi-turkce-dublaj-izle738.jpg"
    },
    {
        "title": "Vavien",
        "link": "https://www.fullhdfilmizlesene.live/film/vavien",
        "imdb": "7.5",
        "year": "2009",
        "image": "https://img.fullhdfilmizlesene.live/poster/film/fullhd-vavien-filmi-izle.jpg"
    },
    {
        "title": "Kehanet",
        "link": "https://www.fullhdfilmizlesene.live/film/kehanet",
        "imdb": "6.2",
        "year": "2009",
        "image": "https://img.fullhdfilmizlesene.live/poster/film/kehanet-film-izle-turkce-dublaj980.jpg"
    },
    {
        "title": "Onun Hakkında Herşey",
        "link": "https://www.fullhdfilmizlesene.live/film/onun-hakkinda-hersey-2",
        "imdb": "4.8",
        "year": "2009",
        "image": "https://img.fullhdfilmizlesene.live/poster/film/onun-hakkinda-hersey-hd-film-izle828.jpg"
    },
    {
        "title": "Karanlığa Karşı",
        "link": "https://www.fullhdfilmizlesene.live/film/karanliga-karsi",
        "imdb": "3.1",
        "year": "2009",
        "image": "https://img.fullhdfilmizlesene.live/poster/film/fullhd-karanliga-karsi-filmi-turkce-dublaj-izle.jpg"
    },
    {
        "title": "Lopnor Tomb",
        "link": "https://www.fullhdfilmizlesene.live/film/lopnor-tomb",
        "imdb": "5.1",
        "year": "2023",
        "image": "https://img.fullhdfilmizlesene.live/poster/film/fullhd-lopnor-tomb.jpg"
    },
    {
        "title": "The Holding",
        "link": "https://www.fullhdfilmizlesene.live/film/the-holding",
        "imdb": "4.7",
        "year": "2011",
        "image": "https://img.fullhdfilmizlesene.live/poster/film/993a18168a1bd97d32c6a8d634f7af87.jpg"
    },
    {
        "title": "Kar Beyaz",
        "link": "https://www.fullhdfilmizlesene.live/film/kar-beyaz-3",
        "imdb": "5.9",
        "year": "2010",
        "image": "https://img.fullhdfilmizlesene.live/poster/film/e0e510bf801c825138e2a7e96bc63f9e.jpg"
    },
    {
        "title": "Hırsız Kedi Pariste",
        "link": "https://www.fullhdfilmizlesene.live/film/hirsiz-kedi-pariste",
        "imdb": "6.9",
        "year": "2010",
        "image": "https://img.fullhdfilmizlesene.live/poster/film/fullhd-hirsiz-kedi-pariste-turkce-dublaj-izle.jpg"
    },
    {
        "title": "Zombilerin Şafağı",
        "link": "https://www.fullhdfilmizlesene.live/film/zombilerin-safagi-2",
        "imdb": "7.9",
        "year": "2004",
        "image": "https://img.fullhdfilmizlesene.live/poster/film/4aa2668cc88b212de58dd9d873e3aca8.jpg"
    },
    {
        "title": "Savaş Oyunları",
        "link": "https://www.fullhdfilmizlesene.live/film/savas-oyunlari",
        "imdb": "4.5",
        "year": "2011",
        "image": "https://img.fullhdfilmizlesene.live/poster/film/fullhd-savas-oyunlari-turkce-dublaj-izle-hd-720p.jpg"
    },
    {
        "title": "Korku Gecesi",
        "link": "https://www.fullhdfilmizlesene.live/film/korku-gecesi-3",
        "imdb": "6.4",
        "year": "2011",
        "image": "https://img.fullhdfilmizlesene.live/poster/film/fullhd-84533959534019.jpg"
    },
    {
        "title": "Cenneti Beklerken",
        "link": "https://www.fullhdfilmizlesene.live/film/cenneti-beklerken",
        "imdb": "6.6",
        "year": "2006",
        "image": "https://img.fullhdfilmizlesene.live/poster/film/c0523a61e7210ead9ce052949ef7a62a.jpg"
    },
    {
        "title": "Unutulmuş Düşler Mağarası",
        "link": "https://www.fullhdfilmizlesene.live/film/unutulmus-dusler-magarasi",
        "imdb": "7.4",
        "year": "2010",
        "image": "https://img.fullhdfilmizlesene.live/poster/film/a1af8d3c2ee139e865a2271a83db61a9.jpg"
    },
    {
        "title": "Süper Melez",
        "link": "https://www.fullhdfilmizlesene.live/film/super-melez",
        "imdb": "4.1",
        "year": "2010",
        "image": "https://img.fullhdfilmizlesene.live/poster/film/b72d95f033cc966a1a24985869df7fa5.jpg"
    },
    {
        "title": "Kirli Sırlar",
        "link": "https://www.fullhdfilmizlesene.live/film/kirli-sirlar",
        "imdb": "6.7",
        "year": "2006",
        "image": "https://img.fullhdfilmizlesene.live/poster/film/88da335e7133b64a5afb2d6cfcb29f67.jpg"
    },
    {
        "title": "16 Blok",
        "link": "https://www.fullhdfilmizlesene.live/film/16-blok",
        "imdb": "6.6",
        "year": "2006",
        "image": "https://img.fullhdfilmizlesene.live/poster/film/16-blok-filmi-full-hd-izle-turkce-dublaj297.jpg"
    },
    {
        "title": "Elizabeth Altın Çağ",
        "link": "https://www.fullhdfilmizlesene.live/film/elizabeth-altin-cag",
        "imdb": "6.8",
        "year": "2007",
        "image": "https://img.fullhdfilmizlesene.live/poster/film/elizabeth-altin-cag-bedava-seyret65.jpg"
    }
]