[
    {
        "title": "Labor Day",
        "link": "https://www.fullhdfilmizlesene.live/film/labor-day",
        "imdb": "6.9",
        "year": "2013",
        "image": "https://img.fullhdfilmizlesene.live/poster/film/fullhd-labor-day.jpg"
    },
    {
        "title": "Aslanın Kalbi",
        "link": "https://www.fullhdfilmizlesene.live/film/aslanin-kalbi",
        "imdb": "7.0",
        "year": "2013",
        "image": "https://img.fullhdfilmizlesene.live/poster/film/fullhd-aslanin-kalbi-heart-of-a-lion.jpg"
    },
    {
        "title": "Hirokin: The Last Samurai",
        "link": "https://www.fullhdfilmizlesene.live/film/hirokin-the-last-samurai",
        "imdb": "3.3",
        "year": "2012",
        "image": "https://img.fullhdfilmizlesene.live/poster/film/fullhd-hirokin-the-last-samurai.jpg"
    },
    {
        "title": "Aile Sırları",
        "link": "https://www.fullhdfilmizlesene.live/film/aile-sirlari-4",
        "imdb": "7.2",
        "year": "2013",
        "image": "https://img.fullhdfilmizlesene.live/poster/film/fullhd-aile-sirlari-august-osage-county.jpg"
    },
    {
        "title": "Doğayla Mücadele",
        "link": "https://www.fullhdfilmizlesene.live/film/dogayla-mucadele",
        "imdb": "4.5",
        "year": "2013",
        "image": "https://img.fullhdfilmizlesene.live/poster/film/fullhd-dogayla-mucadele-against-the-wild.jpg"
    },
    {
        "title": "Het Tweede Gelaat",
        "link": "https://www.fullhdfilmizlesene.live/film/het-tweede-gelaat",
        "imdb": "6.3",
        "year": "2017",
        "image": "https://img.fullhdfilmizlesene.live/poster/film/fullhd-het-tweede-gelaat.jpg"
    },
    {
        "title": "Ferdinand",
        "link": "https://www.fullhdfilmizlesene.live/film/ferdinand",
        "imdb": "6.7",
        "year": "2017",
        "image": "https://img.fullhdfilmizlesene.live/poster/film/fullhd-ferdinand-animasyon-izle.jpg"
    },
    {
        "title": "Curvature",
        "link": "https://www.fullhdfilmizlesene.live/film/curvature",
        "imdb": "4.7",
        "year": "2017",
        "image": "https://img.fullhdfilmizlesene.live/poster/film/fullhd-curvature.jpg"
    },
    {
        "title": "Ganimet",
        "link": "https://www.fullhdfilmizlesene.live/film/ganimet",
        "imdb": "7.3",
        "year": "2017",
        "image": "https://img.fullhdfilmizlesene.live/poster/film/fullhd-ganimet-trophy.jpg"
    },
    {
        "title": "Gangster Land",
        "link": "https://www.fullhdfilmizlesene.live/film/gangster-land",
        "imdb": "4.3",
        "year": "2017",
        "image": "https://img.fullhdfilmizlesene.live/poster/film/fullhd-gangster-land-in-the-absence-of-good-men.jpg"
    },
    {
        "title": "Yemin",
        "link": "https://www.fullhdfilmizlesene.live/film/yemin",
        "imdb": "6.4",
        "year": "2016",
        "image": "https://img.fullhdfilmizlesene.live/poster/film/fullhd-yemin-the-oath.jpg"
    },
    {
        "title": "Tatilde Evdeyim",
        "link": "https://www.fullhdfilmizlesene.live/film/tatilde-evdeyim",
        "imdb": "4.9",
        "year": "2017",
        "image": "https://img.fullhdfilmizlesene.live/poster/film/fullhd-tatilde-evdeyim-home-for-the-holidays.jpg"
    },
    {
        "title": "Umut Çiftliği",
        "link": "https://www.fullhdfilmizlesene.live/film/umut-ciftligi",
        "imdb": "5.8",
        "year": "2017",
        "image": "https://img.fullhdfilmizlesene.live/poster/film/fullhd-umut-ciftligi-running-wild.jpg"
    },
    {
        "title": "Umrika",
        "link": "https://www.fullhdfilmizlesene.live/film/umrika",
        "imdb": "6.6",
        "year": "2015",
        "image": "https://img.fullhdfilmizlesene.live/poster/film/fullhd-umrika.jpg"
    },
    {
        "title": "Hellraiser: Judgment",
        "link": "https://www.fullhdfilmizlesene.live/film/hellraiser-judgment",
        "imdb": "4.3",
        "year": "2018",
        "image": "https://img.fullhdfilmizlesene.live/poster/film/fullhd-hellraiser-judgment.jpg"
    },
    {
        "title": "Bhaagamathie",
        "link": "https://www.fullhdfilmizlesene.live/film/bhaagamathie",
        "imdb": "7.0",
        "year": "2018",
        "image": "https://img.fullhdfilmizlesene.live/poster/film/fullhd-bhaagamathie.jpg"
    },
    {
        "title": "Star",
        "link": "https://www.fullhdfilmizlesene.live/film/star",
        "imdb": "6.3",
        "year": "2017",
        "image": "https://img.fullhdfilmizlesene.live/poster/film/fullhd-star-the-star.jpg"
    },
    {
        "title": "Immigration Game",
        "link": "https://www.fullhdfilmizlesene.live/film/immigration-game",
        "imdb": "3.4",
        "year": "2017",
        "image": "https://img.fullhdfilmizlesene.live/poster/film/fullhd-immigration-game.jpg"
    }
]