[
    {
        "title": "Son Oyun",
        "link": "https://www.fullhdfilmizlesene.live/film/son-oyun",
        "imdb": "6.0",
        "year": "2009",
        "image": "https://img.fullhdfilmizlesene.live/poster/film/fullhd-son-oyun-turkce-dublaj-izle.jpg"
    },
    {
        "title": "Sibirya Ekspresi",
        "link": "https://www.fullhdfilmizlesene.live/film/sibirya-ekspresi",
        "imdb": "6.6",
        "year": "2008",
        "image": "https://img.fullhdfilmizlesene.live/poster/film/fullhd-27542958175763.jpg"
    },
    {
        "title": "Salgın",
        "link": "https://www.fullhdfilmizlesene.live/film/salgin-2",
        "imdb": "6.5",
        "year": "2010",
        "image": "https://img.fullhdfilmizlesene.live/poster/film/fullhd-52713181823492.jpg"
    },
    {
        "title": "Büyülü Tat",
        "link": "https://www.fullhdfilmizlesene.live/film/buyulu-tat",
        "imdb": "6.3",
        "year": "2008",
        "image": "https://img.fullhdfilmizlesene.live/poster/film/fullhd-2364984015002.jpg"
    },
    {
        "title": "Kısırdöngü",
        "link": "https://www.fullhdfilmizlesene.live/film/kisirdongu",
        "imdb": "7.4",
        "year": "2009",
        "image": "https://img.fullhdfilmizlesene.live/poster/film/fullhd-11881681624799.jpg"
    },
    {
        "title": "Gol 3",
        "link": "https://www.fullhdfilmizlesene.live/film/gol-3-2",
        "imdb": "3.2",
        "year": "2009",
        "image": "https://img.fullhdfilmizlesene.live/poster/film/fullhd-64495287556201.jpg"
    },
    {
        "title": "Gol 2",
        "link": "https://www.fullhdfilmizlesene.live/film/gol-2",
        "imdb": "5.8",
        "year": "2007",
        "image": "https://img.fullhdfilmizlesene.live/poster/film/fullhd-86752842552959.jpg"
    },
    {
        "title": "Gol 1",
        "link": "https://www.fullhdfilmizlesene.live/film/gol-1",
        "imdb": "6.7",
        "year": "2005",
        "image": "https://img.fullhdfilmizlesene.live/poster/film/fullhd-74643197236582.jpg"
    },
    {
        "title": "Süper Tanker",
        "link": "https://www.fullhdfilmizlesene.live/film/super-tanker",
        "imdb": "2.8",
        "year": "2011",
        "image": "https://img.fullhdfilmizlesene.live/poster/film/fullhd-77000871440395.jpg"
    },
    {
        "title": "Sis Perdesi",
        "link": "https://www.fullhdfilmizlesene.live/film/sis-perdesi",
        "imdb": "5.1",
        "year": "2010",
        "image": "https://img.fullhdfilmizlesene.live/poster/film/fullhd-52059557987377.jpg"
    },
    {
        "title": "Ölüm Fırtınası",
        "link": "https://www.fullhdfilmizlesene.live/film/olum-firtinasi",
        "imdb": "5.8",
        "year": "2007",
        "image": "https://img.fullhdfilmizlesene.live/poster/film/fullhd-olum-firtinasi-turkce-dublaj-izle.jpg"
    },
    {
        "title": "Silah",
        "link": "https://www.fullhdfilmizlesene.live/film/silah",
        "imdb": "3.8",
        "year": "2010",
        "image": "https://img.fullhdfilmizlesene.live/poster/film/fullhd-silah-turkce-dublaj-izle.jpg"
    },
    {
        "title": "Ölülerin Günlüğü",
        "link": "https://www.fullhdfilmizlesene.live/film/olulerin-gunlugu",
        "imdb": "5.5",
        "year": "2007",
        "image": "https://img.fullhdfilmizlesene.live/poster/film/fullhd-olulerin-gunlugu-turkce-dublaj-izle-full.jpg"
    },
    {
        "title": "Kamyoncu",
        "link": "https://www.fullhdfilmizlesene.live/film/kamyoncu",
        "imdb": "6.5",
        "year": "2008",
        "image": "https://img.fullhdfilmizlesene.live/poster/film/fullhd-kamyoncu-turkce-dublaj-izle.jpg"
    },
    {
        "title": "İntikamın Bedeli",
        "link": "https://www.fullhdfilmizlesene.live/film/intikamin-bedeli",
        "imdb": "6.1",
        "year": "2011",
        "image": "https://img.fullhdfilmizlesene.live/poster/film/fullhd-59760436788201.jpg"
    },
    {
        "title": "Düğün Savaşları",
        "link": "https://www.fullhdfilmizlesene.live/film/dugun-savaslari",
        "imdb": "6.0",
        "year": "2006",
        "image": "https://img.fullhdfilmizlesene.live/poster/film/fullhd-58115525497123.jpg"
    },
    {
        "title": "Diplomat",
        "link": "https://www.fullhdfilmizlesene.live/film/diplomat",
        "imdb": "5.4",
        "year": "2009",
        "image": "https://img.fullhdfilmizlesene.live/poster/film/fullhd-1873510237783.jpg"
    },
    {
        "title": "Amerikan Usulü Bir İlişki",
        "link": "https://www.fullhdfilmizlesene.live/film/amerikan-usulu-bir-iliski",
        "imdb": "6.1",
        "year": "2009",
        "image": "https://img.fullhdfilmizlesene.live/poster/film/fullhd-6586608383804.jpg"
    }
]