[
    {
        "title": "Vatikan Kayıtları",
        "link": "https://www.fullhdfilmizlesene.live/film/vatikan-kayitlari",
        "imdb": "4.7",
        "year": "2015",
        "image": "https://img.fullhdfilmizlesene.live/poster/film/fullhd-the-vatican-tapes.jpg"
    },
    {
        "title": "Advantageous",
        "link": "https://www.fullhdfilmizlesene.live/film/advantageous",
        "imdb": "6.1",
        "year": "2015",
        "image": "https://img.fullhdfilmizlesene.live/poster/film/fullhd-advantageous-film-izle.jpg"
    },
    {
        "title": "Centilmen",
        "link": "https://www.fullhdfilmizlesene.live/film/centilmen",
        "imdb": "6.2",
        "year": "2014",
        "image": "https://img.fullhdfilmizlesene.live/poster/film/fullhd-centilmen-gentlemen.jpg"
    },
    {
        "title": "Ziyaret",
        "link": "https://www.fullhdfilmizlesene.live/film/ziyaret",
        "imdb": "6.3",
        "year": "2015",
        "image": "https://img.fullhdfilmizlesene.live/poster/film/fullhd-ziyaret-the-visit.jpg"
    },
    {
        "title": "Gece Bekçisi",
        "link": "https://www.fullhdfilmizlesene.live/film/gece-bekcisi",
        "imdb": "6.2",
        "year": "2015",
        "image": "https://img.fullhdfilmizlesene.live/poster/film/fullhd-gece-bekcisi-jamais-de-la-vie.jpg"
    },
    {
        "title": "Aşk ve Merhamet",
        "link": "https://www.fullhdfilmizlesene.live/film/ask-ve-merhamet",
        "imdb": "7.4",
        "year": "2014",
        "image": "https://img.fullhdfilmizlesene.live/poster/film/fullhd-ask-ve-merhamet-love-mercy.jpg"
    },
    {
        "title": "Noel Sırrı",
        "link": "https://www.fullhdfilmizlesene.live/film/noel-sirri",
        "imdb": "7.3",
        "year": "2014",
        "image": "https://img.fullhdfilmizlesene.live/poster/film/fullhd-noel-sirri-the-christmas-secret.jpg"
    },
    {
        "title": "Ağır Abiler 3",
        "link": "https://www.fullhdfilmizlesene.live/film/agir-abiler-3",
        "imdb": "5.3",
        "year": "2015",
        "image": "https://img.fullhdfilmizlesene.live/poster/film/fullhd-agir-abiler-3-bad-ass-3-bad-asses-on-the-bayou.jpg"
    },
    {
        "title": "Stajyer",
        "link": "https://www.fullhdfilmizlesene.live/film/stajyer",
        "imdb": "7.1",
        "year": "2015",
        "image": "https://img.fullhdfilmizlesene.live/poster/film/fullhd-stajyer-the-intern.jpg"
    },
    {
        "title": "Marslı",
        "link": "https://www.fullhdfilmizlesene.live/film/marsli",
        "imdb": "8.0",
        "year": "2015",
        "image": "https://img.fullhdfilmizlesene.live/poster/film/fullhd-marsli-the-martian-2015-filmi-full-izle.jpg"
    },
    {
        "title": "Bay Heineken'i Kaçırmak",
        "link": "https://www.fullhdfilmizlesene.live/film/bay-heineken-i-kacirmak",
        "imdb": "6.1",
        "year": "2015",
        "image": "https://img.fullhdfilmizlesene.live/poster/film/fullhd-bay-heinekeni-kacirmak-kidnapping-freddy-heineken.jpg"
    },
    {
        "title": "İnsan Ticareti",
        "link": "https://www.fullhdfilmizlesene.live/film/insan-ticareti-2",
        "imdb": "5.6",
        "year": "2014",
        "image": "https://img.fullhdfilmizlesene.live/poster/film/fullhd-skin-trade-film-izle.jpg"
    },
    {
        "title": "Koca Ayak",
        "link": "https://www.fullhdfilmizlesene.live/film/koca-ayak",
        "imdb": "5.1",
        "year": "2013",
        "image": "https://img.fullhdfilmizlesene.live/poster/film/fullhd-koca-ayak-willow-creek.jpg"
    },
    {
        "title": "Deniz Feneri",
        "link": "https://www.fullhdfilmizlesene.live/film/deniz-feneri",
        "imdb": "5.8",
        "year": "2015",
        "image": "https://img.fullhdfilmizlesene.live/poster/film/fullhd-deniz-feneri-safelight.jpg"
    },
    {
        "title": "Kutupta Macera",
        "link": "https://www.fullhdfilmizlesene.live/film/kutupta-macera",
        "imdb": "6.0",
        "year": "2014",
        "image": "https://img.fullhdfilmizlesene.live/poster/film/fullhd-kutupta-macera-operasjon-arktis.jpg"
    },
    {
        "title": "Ölüm Yolu",
        "link": "https://www.fullhdfilmizlesene.live/film/olum-yolu-3",
        "imdb": "6.2",
        "year": "2014",
        "image": "https://img.fullhdfilmizlesene.live/poster/film/fullhd-wyrmwood-hd-film-izle.jpg"
    },
    {
        "title": "Çılgın Tatil",
        "link": "https://www.fullhdfilmizlesene.live/film/cilgin-tatil",
        "imdb": "6.0",
        "year": "2014",
        "image": "https://img.fullhdfilmizlesene.live/poster/film/fullhd-cilgin-tatil-selfie.jpg"
    },
    {
        "title": "Büyük Plan",
        "link": "https://www.fullhdfilmizlesene.live/film/buyuk-plan",
        "imdb": "5.4",
        "year": "2015",
        "image": "https://img.fullhdfilmizlesene.live/poster/film/fullhd-buyuk-plan-the-master-plan.jpg"
    }
]