[
    {
        "title": "Son umut",
        "link": "https://www.fullhdfilmizlesene.live/film/son-umut-2",
        "imdb": "7.9",
        "year": "2006",
        "image": "https://img.fullhdfilmizlesene.live/poster/film/children-of-men-79222.jpg"
    },
    {
        "title": "Hyde",
        "link": "https://www.fullhdfilmizlesene.live/film/hyde",
        "imdb": "4.1",
        "year": "2019",
        "image": "https://img.fullhdfilmizlesene.live/poster/film/hyde-94386.jpg"
    },
    {
        "title": "The Resort",
        "link": "https://www.fullhdfilmizlesene.live/film/the-resort",
        "imdb": "3.1",
        "year": "2021",
        "image": "https://img.fullhdfilmizlesene.live/poster/film/the-resort-81445.jpg"
    },
    {
        "title": "Just Say Yes",
        "link": "https://www.fullhdfilmizlesene.live/film/just-say-yes",
        "imdb": "4.6",
        "year": "2021",
        "image": "https://img.fullhdfilmizlesene.live/poster/film/just-say-yes-71640.jpg"
    },
    {
        "title": "Echo 8",
        "link": "https://www.fullhdfilmizlesene.live/film/echo-8",
        "imdb": "3.9",
        "year": "2024",
        "image": "https://img.fullhdfilmizlesene.live/poster/film/echo-8-820.jpg"
    },
    {
        "title": "Assassin's Guild",
        "link": "https://www.fullhdfilmizlesene.live/film/assassin-s-guild",
        "imdb": "3.7",
        "year": "2024",
        "image": "https://img.fullhdfilmizlesene.live/poster/film/assassins-guild-2513.jpg"
    },
    {
        "title": "Ash",
        "link": "https://www.fullhdfilmizlesene.live/film/ash-2025",
        "imdb": "5.8",
        "year": "2025",
        "image": "https://img.fullhdfilmizlesene.live/poster/film/ash-6-9091.jpg"
    },
    {
        "title": "100 millions!",
        "link": "https://www.fullhdfilmizlesene.live/film/100-millions",
        "imdb": "4.2",
        "year": "2025",
        "image": "https://img.fullhdfilmizlesene.live/poster/film/100-millions-6065.jpg"
    },
    {
        "title": "Warden",
        "link": "https://www.fullhdfilmizlesene.live/film/warden",
        "imdb": "5.0",
        "year": "2025",
        "image": "https://img.fullhdfilmizlesene.live/poster/film/warden-9671.jpg"
    },
    {
        "title": "Wanita Ahli Neraka",
        "link": "https://www.fullhdfilmizlesene.live/film/wanita-ahli-neraka",
        "imdb": "5.2",
        "year": "2024",
        "image": "https://img.fullhdfilmizlesene.live/poster/film/wanita-ahli-neraka-4963.jpg"
    },
    {
        "title": "Tebusan Dosa",
        "link": "https://www.fullhdfilmizlesene.live/film/tebusan-dosa",
        "imdb": "6.0",
        "year": "2024",
        "image": "https://img.fullhdfilmizlesene.live/poster/film/tebusan-dosa-5535.jpg"
    },
    {
        "title": "The Parenting",
        "link": "https://www.fullhdfilmizlesene.live/film/the-parenting",
        "imdb": "5.7",
        "year": "2025",
        "image": "https://img.fullhdfilmizlesene.live/poster/film/the-parenting-5610.jpg"
    },
    {
        "title": "Sunray: Fallen Soldier",
        "link": "https://www.fullhdfilmizlesene.live/film/sunray-fallen-soldier",
        "imdb": "4.3",
        "year": "2024",
        "image": "https://img.fullhdfilmizlesene.live/poster/film/sunray-fallen-soldier-5955.jpg"
    },
    {
        "title": "The Alto Knights",
        "link": "https://www.fullhdfilmizlesene.live/film/the-alto-knights",
        "imdb": "5.7",
        "year": "2025",
        "image": "https://img.fullhdfilmizlesene.live/poster/film/the-alto-knights-7010.jpg"
    },
    {
        "title": "Stereoscope",
        "link": "https://www.fullhdfilmizlesene.live/film/stereoscope",
        "imdb": "4.1",
        "year": "2024",
        "image": "https://img.fullhdfilmizlesene.live/poster/film/stereoscope-3330.jpg"
    },
    {
        "title": "Striking Rescue",
        "link": "https://www.fullhdfilmizlesene.live/film/striking-rescue",
        "imdb": "5.6",
        "year": "2024",
        "image": "https://img.fullhdfilmizlesene.live/poster/film/striking-rescue-8885.jpg"
    },
    {
        "title": "Mystery Island: Winner Takes All",
        "link": "https://www.fullhdfilmizlesene.live/film/mystery-island-winner-takes-all",
        "imdb": "5.8",
        "year": "2025",
        "image": "https://img.fullhdfilmizlesene.live/poster/film/mystery-island-winner-takes-all-180.jpg"
    },
    {
        "title": "Long Gone Heroes",
        "link": "https://www.fullhdfilmizlesene.live/film/long-gone-heroes",
        "imdb": "5.2",
        "year": "2024",
        "image": "https://img.fullhdfilmizlesene.live/poster/film/long-gone-heroes-5126.jpg"
    }
]