[
    {
        "title": "Tall, Dark, and Dangerous",
        "link": "https://www.fullhdfilmizlesene.live/film/tall-dark-and-dangerous",
        "imdb": "4.4",
        "year": "2024",
        "image": "https://img.fullhdfilmizlesene.live/poster/film/tall-dark-and-dangerous-63726.jpg"
    },
    {
        "title": "Suncoast",
        "link": "https://www.fullhdfilmizlesene.live/film/suncoast",
        "imdb": "6.6",
        "year": "2024",
        "image": "https://img.fullhdfilmizlesene.live/poster/film/suncoast-40243.jpg"
    },
    {
        "title": "Skeletons in the Closet",
        "link": "https://www.fullhdfilmizlesene.live/film/skeletons-in-the-closet",
        "imdb": "3.1",
        "year": "2024",
        "image": "https://img.fullhdfilmizlesene.live/poster/film/skeletons-in-the-closet-91025.jpg"
    },
    {
        "title": "Silent Night in Algona",
        "link": "https://www.fullhdfilmizlesene.live/film/silent-night-in-algona",
        "imdb": "7.5",
        "year": "2022",
        "image": "https://img.fullhdfilmizlesene.live/poster/film/silent-night-in-algona-40029.jpg"
    },
    {
        "title": "KillHer",
        "link": "https://www.fullhdfilmizlesene.live/film/killher",
        "imdb": "4.2",
        "year": "2022",
        "image": "https://img.fullhdfilmizlesene.live/poster/film/killher-24514.jpg"
    },
    {
        "title": "El Roomie",
        "link": "https://www.fullhdfilmizlesene.live/film/el-roomie",
        "imdb": "6.0",
        "year": "2024",
        "image": "https://img.fullhdfilmizlesene.live/poster/film/el-roomie-79763.jpg"
    },
    {
        "title": "A Tale of Shemroon",
        "link": "https://www.fullhdfilmizlesene.live/film/a-tale-of-shemroon",
        "imdb": "5.7",
        "year": "2022",
        "image": "https://img.fullhdfilmizlesene.live/poster/film/a-tale-of-shemroon-12934.jpg"
    },
    {
        "title": "The Who Incident",
        "link": "https://www.fullhdfilmizlesene.live/film/the-who-incident",
        "imdb": "4.6",
        "year": "2023",
        "image": "https://img.fullhdfilmizlesene.live/poster/film/the-who-incident-10453.jpg"
    },
    {
        "title": "The Circle of Death",
        "link": "https://www.fullhdfilmizlesene.live/film/the-circle-of-death",
        "imdb": "4.4",
        "year": "2023",
        "image": "https://img.fullhdfilmizlesene.live/poster/film/the-circle-of-death-15769.jpg"
    },
    {
        "title": "Tales of Babylon",
        "link": "https://www.fullhdfilmizlesene.live/film/tales-of-babylon",
        "imdb": "6.6",
        "year": "2023",
        "image": "https://img.fullhdfilmizlesene.live/poster/film/tales-of-babylon-29589.jpg"
    },
    {
        "title": "Chapel",
        "link": "https://www.fullhdfilmizlesene.live/film/chapel",
        "imdb": "3.7",
        "year": "2024",
        "image": "https://img.fullhdfilmizlesene.live/poster/film/chapel-36309.jpg"
    },
    {
        "title": "Abigail",
        "link": "https://www.fullhdfilmizlesene.live/film/abigail",
        "imdb": "6.4",
        "year": "2023",
        "image": "https://img.fullhdfilmizlesene.live/poster/film/abigail-3-61469.jpg"
    },
    {
        "title": "The Old Way",
        "link": "https://www.fullhdfilmizlesene.live/film/the-old-way",
        "imdb": "5.5",
        "year": "2023",
        "image": "https://img.fullhdfilmizlesene.live/poster/film/the-old-way-2-60477.jpg"
    },
    {
        "title": "Weldi",
        "link": "https://www.fullhdfilmizlesene.live/film/weldi",
        "imdb": "6.5",
        "year": "2018",
        "image": "https://img.fullhdfilmizlesene.live/poster/film/weldi-dear-son-85831.jpg"
    },
    {
        "title": "Şantaj",
        "link": "https://www.fullhdfilmizlesene.live/film/santaj",
        "imdb": "6.2",
        "year": "2017",
        "image": "https://img.fullhdfilmizlesene.live/poster/film/santaj-extortion-2-64129.jpg"
    },
    {
        "title": "Island of Shadows",
        "link": "https://www.fullhdfilmizlesene.live/film/island-of-shadows",
        "imdb": "5.0",
        "year": "2020",
        "image": "https://img.fullhdfilmizlesene.live/poster/film/island-of-shadows-63199.jpg"
    },
    {
        "title": "Örümcek-Adam: Eve Dönüş Yok",
        "link": "https://www.fullhdfilmizlesene.live/film/orumcek-adam-eve-donus-yok",
        "imdb": "8.2",
        "year": "2021",
        "image": "https://img.fullhdfilmizlesene.live/poster/film/orumcek-adam-eve-donus-yok-izle-1-16915.jpg"
    },
    {
        "title": "Harry Potter 1 Felsefe Taşı",
        "link": "https://www.fullhdfilmizlesene.live/film/harry-potter-1-felsefe-tasi",
        "imdb": "7.6",
        "year": "2001",
        "image": "https://img.fullhdfilmizlesene.live/poster/film/fullhd-harry-potter-ve-felsefe-tasi-filmini-full-hd-izle.jpg"
    }
]