[
    {
        "title": "Ruh",
        "link": "https://www.fullhdfilmizlesene.live/film/ruh-2012",
        "imdb": "5.7",
        "year": "2012",
        "image": "https://img.fullhdfilmizlesene.live/poster/film/fullhd-ruh-the-pact.jpg"
    },
    {
        "title": "Tünel Fareleri",
        "link": "https://www.fullhdfilmizlesene.live/film/tunel-fareleri",
        "imdb": "4.8",
        "year": "2008",
        "image": "https://img.fullhdfilmizlesene.live/poster/film/tunel-fareleri-tunnel-rats-fhd1-9132.jpg"
    },
    {
        "title": "Cesur Balık",
        "link": "https://www.fullhdfilmizlesene.live/film/cesur-balik",
        "imdb": "4.1",
        "year": "2006",
        "image": "https://img.fullhdfilmizlesene.live/poster/film/fullhd-33935952791944.jpg"
    },
    {
        "title": "Acı",
        "link": "https://www.fullhdfilmizlesene.live/film/aci-2012",
        "imdb": "7.1",
        "year": "2012",
        "image": "https://img.fullhdfilmizlesene.live/poster/film/fullhd-aci-pieta.jpg"
    },
    {
        "title": "Amsterdam Baskını",
        "link": "https://www.fullhdfilmizlesene.live/film/amsterdam-baskini",
        "imdb": "2.6",
        "year": "2011",
        "image": "https://img.fullhdfilmizlesene.live/poster/film/fullhd-amsterdam-baskini-amsterdam-heavy.jpg"
    },
    {
        "title": "Gözcü",
        "link": "https://www.fullhdfilmizlesene.live/film/gozcu-2",
        "imdb": "5.7",
        "year": "2012",
        "image": "https://img.fullhdfilmizlesene.live/poster/film/fullhd-gozcu-le-guetteur.jpg"
    },
    {
        "title": "Kanun Yolunda",
        "link": "https://www.fullhdfilmizlesene.live/film/kanun-yolunda",
        "imdb": "6.4",
        "year": "1977",
        "image": "https://img.fullhdfilmizlesene.live/poster/film/fullhd-kanun-yolunda-the-gauntlet.jpg"
    },
    {
        "title": "Beşirle Vals",
        "link": "https://www.fullhdfilmizlesene.live/film/besirle-vals",
        "imdb": "8.0",
        "year": "2008",
        "image": "https://img.fullhdfilmizlesene.live/poster/film/fullhd-vals-im-bashir.jpg"
    },
    {
        "title": "Bir Mafya Hikayesi",
        "link": "https://www.fullhdfilmizlesene.live/film/bir-mafya-hikayesi",
        "imdb": "6.9",
        "year": "2011",
        "image": "https://img.fullhdfilmizlesene.live/poster/film/fullhd-bir-mafya-hikayesi-a-gang-story.jpg"
    },
    {
        "title": "Kızılmaske",
        "link": "https://www.fullhdfilmizlesene.live/film/kizilmaske",
        "imdb": "5.1",
        "year": "2009",
        "image": "https://img.fullhdfilmizlesene.live/poster/film/fullhd-kizilmaske-the-phantom.jpg"
    },
    {
        "title": "Acil Teslimat",
        "link": "https://www.fullhdfilmizlesene.live/film/acil-teslimat",
        "imdb": "6.5",
        "year": "2012",
        "image": "https://img.fullhdfilmizlesene.live/poster/film/fullhd-acil-teslimat-premium-rush.jpg"
    },
    {
        "title": "Karanlıkta",
        "link": "https://www.fullhdfilmizlesene.live/film/karanlikta",
        "imdb": "7.3",
        "year": "2011",
        "image": "https://img.fullhdfilmizlesene.live/poster/film/fullhd-karanlikta-in-darkness.jpg"
    },
    {
        "title": "Erkeğin Derdi Ceviz Kırmak",
        "link": "https://www.fullhdfilmizlesene.live/film/erkegin-derdi-ceviz-kirmak",
        "imdb": "7.0",
        "year": "2011",
        "image": "https://img.fullhdfilmizlesene.live/poster/film/fullhd-muzi-v-nadeji.jpg"
    },
    {
        "title": "Love",
        "link": "https://www.fullhdfilmizlesene.live/film/love",
        "imdb": "5.4",
        "year": "2011",
        "image": "https://img.fullhdfilmizlesene.live/poster/film/fullhd-love-2.jpg"
    },
    {
        "title": "Bay 3000",
        "link": "https://www.fullhdfilmizlesene.live/film/bay-3000",
        "imdb": "5.6",
        "year": "2004",
        "image": "https://img.fullhdfilmizlesene.live/poster/film/fullhd-bay-3000-mr-3000.jpg"
    },
    {
        "title": "Tuzak",
        "link": "https://www.fullhdfilmizlesene.live/film/tuzak-4",
        "imdb": "6.3",
        "year": "2011",
        "image": "https://img.fullhdfilmizlesene.live/poster/film/fullhd-tuzak-switch.jpg"
    },
    {
        "title": "Blue Like Jazz",
        "link": "https://www.fullhdfilmizlesene.live/film/blue-like-jazz",
        "imdb": "5.8",
        "year": "2012",
        "image": "https://img.fullhdfilmizlesene.live/poster/film/fullhd-blue-like-jazz.jpg"
    },
    {
        "title": "Soar Into The Sun",
        "link": "https://www.fullhdfilmizlesene.live/film/soar-into-the-sun",
        "imdb": "6.1",
        "year": "2012",
        "image": "https://img.fullhdfilmizlesene.live/poster/film/fullhd-soar-into-the-sun-r2b-return-to-base.jpg"
    }
]