[
    {
        "title": "Baang",
        "link": "https://www.fullhdfilmizlesene.live/film/baang",
        "imdb": "3.9",
        "year": "2023",
        "image": "https://img.fullhdfilmizlesene.live/poster/film/baang-81307.jpg"
    },
    {
        "title": "Chang kong zhi wang",
        "link": "https://www.fullhdfilmizlesene.live/film/chang-kong-zhi-wang",
        "imdb": "5.9",
        "year": "2023",
        "image": "https://img.fullhdfilmizlesene.live/poster/film/chang-kong-zhi-wang-86495.jpg"
    },
    {
        "title": "Ocean Rescue",
        "link": "https://www.fullhdfilmizlesene.live/film/ocean-rescue",
        "imdb": "6.9",
        "year": "2023",
        "image": "https://img.fullhdfilmizlesene.live/poster/film/ocean-rescue-67116.jpg"
    },
    {
        "title": "Mutant Ghost Wargirl",
        "link": "https://www.fullhdfilmizlesene.live/film/mutant-ghost-wargirl",
        "imdb": "4.6",
        "year": "2022",
        "image": "https://img.fullhdfilmizlesene.live/poster/film/mutant-ghost-wargirl-35804.jpg"
    },
    {
        "title": "L'etat et moi",
        "link": "https://www.fullhdfilmizlesene.live/film/l-etat-et-moi",
        "imdb": "5.5",
        "year": "2022",
        "image": "https://img.fullhdfilmizlesene.live/poster/film/letat-et-moi-40110.jpg"
    },
    {
        "title": "Janvaris",
        "link": "https://www.fullhdfilmizlesene.live/film/janvaris",
        "imdb": "6.5",
        "year": "2022",
        "image": "https://img.fullhdfilmizlesene.live/poster/film/janvaris-95991.jpg"
    },
    {
        "title": "Bone Cold",
        "link": "https://www.fullhdfilmizlesene.live/film/bone-cold",
        "imdb": "5.1",
        "year": "2022",
        "image": "https://img.fullhdfilmizlesene.live/poster/film/bone-cold-63641.jpg"
    },
    {
        "title": "Jurassic Shark 3: Seavenge",
        "link": "https://www.fullhdfilmizlesene.live/film/jurassic-shark-3-seavenge",
        "imdb": "2.2",
        "year": "2023",
        "image": "https://img.fullhdfilmizlesene.live/poster/film/jurassic-shark-3-seavenge-78927.jpg"
    },
    {
        "title": "Captive",
        "link": "https://www.fullhdfilmizlesene.live/film/captive-3",
        "imdb": "4.1",
        "year": "2023",
        "image": "https://img.fullhdfilmizlesene.live/poster/film/captive-3-23677.jpg"
    },
    {
        "title": "Rüyanın Peşinde",
        "link": "https://www.fullhdfilmizlesene.live/film/ruyanin-pesinde",
        "imdb": "6.5",
        "year": "2023",
        "image": "https://img.fullhdfilmizlesene.live/poster/film/ruyanin-pesinde-deurim-50791.jpg"
    },
    {
        "title": "47 Ronin Kılıcı",
        "link": "https://www.fullhdfilmizlesene.live/film/47-ronin-kilici",
        "imdb": "4.7",
        "year": "2022",
        "image": "https://img.fullhdfilmizlesene.live/poster/film/blade-of-the-47-ronin-51161.jpg"
    },
    {
        "title": "47 ronin",
        "link": "https://www.fullhdfilmizlesene.live/film/47-ronin",
        "imdb": "6.2",
        "year": "2013",
        "image": "https://img.fullhdfilmizlesene.live/poster/film/fullhd-47-ronin-film-izle.jpg"
    },
    {
        "title": "Dignitate",
        "link": "https://www.fullhdfilmizlesene.live/film/dignitate",
        "imdb": "5.5",
        "year": "2020",
        "image": "https://img.fullhdfilmizlesene.live/poster/film/dignitate-55814.jpg"
    },
    {
        "title": "Pabuya",
        "link": "https://www.fullhdfilmizlesene.live/film/pabuya",
        "imdb": "4.9",
        "year": "2022",
        "image": "https://img.fullhdfilmizlesene.live/poster/film/pabuya-9183.jpg"
    },
    {
        "title": "The Quantum Devil",
        "link": "https://www.fullhdfilmizlesene.live/film/the-quantum-devil",
        "imdb": "3.5",
        "year": "2023",
        "image": "https://img.fullhdfilmizlesene.live/poster/film/the-quantum-devil-518.jpg"
    },
    {
        "title": "Navigating Christmas",
        "link": "https://www.fullhdfilmizlesene.live/film/navigating-christmas",
        "imdb": "6.4",
        "year": "2023",
        "image": "https://img.fullhdfilmizlesene.live/poster/film/navigating-christmas-24003.jpg"
    },
    {
        "title": "Bilinmeyenler: Kozmik Zaman Makinesi",
        "link": "https://www.fullhdfilmizlesene.live/film/bilinmeyenler-kozmik-zaman-makinesi",
        "imdb": "7.2",
        "year": "2023",
        "image": "https://img.fullhdfilmizlesene.live/poster/film/bilinmeyenler-kozmik-zaman-makinesi-unknown-cosmic-time-machine-7374.jpg"
    },
    {
        "title": "Lange leve bonusfamiljen",
        "link": "https://www.fullhdfilmizlesene.live/film/lange-leve-bonusfamiljen",
        "imdb": "5.2",
        "year": "2022",
        "image": "https://img.fullhdfilmizlesene.live/poster/film/lange-leve-bonusfamiljen-8789.jpg"
    }
]