[
    {
        "title": "Kevin Hart: The Kennedy Center Mark Twain Prize for American Humor",
        "link": "https://www.fullhdfilmizlesene.live/film/kevin-hart-the-kennedy-center-mark-twain-prize-for-american",
        "rapid_link": "",
        "imdb": "6.7",
        "year": "2024",
        "image": "https://img.fullhdfilmizlesene.live/poster/film/kevin-hart-the-kennedy-center-mark-twain-prize-for-american-humor-14533.jpg"
    },
    {
        "title": "Take Cover",
        "link": "https://www.fullhdfilmizlesene.live/film/take-cover",
        "rapid_link": "",
        "imdb": "7.6",
        "year": "2024",
        "image": "https://img.fullhdfilmizlesene.live/poster/film/take-cover-17900.jpg"
    },
    {
        "title": "Azrail",
        "link": "https://www.fullhdfilmizlesene.live/film/azrail",
        "rapid_link": "",
        "imdb": "5.5",
        "year": "2024",
        "image": "https://img.fullhdfilmizlesene.live/poster/film/azrail-azrael-57048.jpg"
    },
    {
        "title": "Mr. Crocket",
        "link": "https://www.fullhdfilmizlesene.live/film/mr-crocket",
        "rapid_link": "",
        "imdb": "5.3",
        "year": "2024",
        "image": "https://img.fullhdfilmizlesene.live/poster/film/mr-crocket-3457.jpg"
    },
    {
        "title": "Seize Them!",
        "link": "https://www.fullhdfilmizlesene.live/film/seize-them",
        "rapid_link": "",
        "imdb": "5.1",
        "year": "2024",
        "image": "https://img.fullhdfilmizlesene.live/poster/film/seize-them-50432.jpg"
    },
    {
        "title": "Hepsini Öldür 2",
        "link": "https://www.fullhdfilmizlesene.live/film/hepsini-oldur-2",
        "rapid_link": "",
        "imdb": "3.8",
        "year": "2024",
        "image": "https://img.fullhdfilmizlesene.live/poster/film/hepsini-oldur-2-kill-em-all-2-70231.jpg"
    },
    {
        "title": "Hepsini Öldür",
        "link": "https://www.fullhdfilmizlesene.live/film/hepsini-oldur",
        "rapid_link": "",
        "imdb": "4.3",
        "year": "2017",
        "image": "https://img.fullhdfilmizlesene.live/poster/film/hepsini-oldur-kill-em-all-11661.jpg"
    },
    {
        "title": "Asi Prenses",
        "link": "https://www.fullhdfilmizlesene.live/film/asi-prenses",
        "rapid_link": "",
        "imdb": "6.1",
        "year": "2021",
        "image": "https://img.fullhdfilmizlesene.live/poster/film/asi-prenses-pil-9604.jpg"
    },
    {
        "title": "İsyan",
        "link": "https://www.fullhdfilmizlesene.live/film/isyan-3",
        "rapid_link": "",
        "imdb": "5.1",
        "year": "2015",
        "image": "https://img.fullhdfilmizlesene.live/poster/film/fullhd-isyan-riot.jpg"
    },
    {
        "title": "Kasap Havası",
        "link": "https://www.fullhdfilmizlesene.live/film/kasap-havasi",
        "rapid_link": "",
        "imdb": "6.2",
        "year": "2015",
        "image": "https://img.fullhdfilmizlesene.live/poster/film/kasap-havasi-84378.jpg"
    },
    {
        "title": "Uprising",
        "link": "https://www.fullhdfilmizlesene.live/film/uprising",
        "rapid_link": "",
        "imdb": "6.5",
        "year": "2024",
        "image": "https://img.fullhdfilmizlesene.live/poster/film/uprising-jeon-ran-87142.jpg"
    },
    {
        "title": "Yalnız Gezegen",
        "link": "https://www.fullhdfilmizlesene.live/film/yalniz-gezegen",
        "rapid_link": "",
        "imdb": "5.9",
        "year": "2024",
        "image": "https://img.fullhdfilmizlesene.live/poster/film/yalniz-gezegen-lonely-planet-74596.jpg"
    },
    {
        "title": "Umudunu Kaybetme",
        "link": "https://www.fullhdfilmizlesene.live/film/umudunu-kaybetme-2",
        "rapid_link": "",
        "imdb": "8.0",
        "year": "2006",
        "image": "https://img.fullhdfilmizlesene.live/poster/film/umudunu-kaybetme-the-pursuit-of-happyness-2-9238.jpg"
    },
    {
        "title": "Paralel Hayatlar",
        "link": "https://www.fullhdfilmizlesene.live/film/paralel-hayatlar",
        "rapid_link": "",
        "imdb": "5.3",
        "year": "2024",
        "image": "https://img.fullhdfilmizlesene.live/poster/film/paralel-hayatlar-el-lugar-de-la-otra-60198.jpg"
    },
    {
        "title": "Büyük Plan",
        "link": "https://www.fullhdfilmizlesene.live/film/buyuk-plan-2",
        "rapid_link": "",
        "imdb": "5.4",
        "year": "2015",
        "image": "https://img.fullhdfilmizlesene.live/poster/film/buyuk-plan-jonssonligan-den-perfekta-stoten-85601.jpg"
    },
    {
        "title": "+1",
        "link": "https://www.fullhdfilmizlesene.live/film/1-2013",
        "rapid_link": "",
        "imdb": "5.5",
        "year": "2013",
        "image": "https://img.fullhdfilmizlesene.live/poster/film/-1-45894.jpg"
    },
    {
        "title": "İnfazcı",
        "link": "https://www.fullhdfilmizlesene.live/film/infazci-2",
        "rapid_link": "",
        "imdb": "6.4",
        "year": "2004",
        "image": "https://img.fullhdfilmizlesene.live/poster/film/infazci-the-punisher-67336.jpg"
    },
    {
        "title": "The Universal Theory",
        "link": "https://www.fullhdfilmizlesene.live/film/the-universal-theory",
        "rapid_link": "",
        "imdb": "6.2",
        "year": "2023",
        "image": "https://img.fullhdfilmizlesene.live/poster/film/the-universal-theory-die-theorie-von-allem-80116.jpg"
    }
]