[
    {
        "title": "Yavaşça Söyle",
        "link": "https://www.fullhdfilmizlesene.live/film/yavasca-soyle",
        "imdb": "4.7",
        "year": "2025",
        "image": "https://img.fullhdfilmizlesene.live/poster/film/yavasca-soyle-dimelo-bajito-29914.jpg",
        "rapid_link": "https://rapidvid.net/vod/v1x87fee76f"
    },
    {
        "title": "Oğul",
        "link": "https://www.fullhdfilmizlesene.live/film/ogul-3",
        "imdb": "3.9",
        "year": "2025",
        "image": "https://img.fullhdfilmizlesene.live/poster/film/ogul-the-carpenter-s-son-23252.jpg",
        "rapid_link": "https://rapidvid.net/vod/v1xea7b11d6"
    },
    {
        "title": "The Secrets We Bury",
        "link": "https://www.fullhdfilmizlesene.live/film/the-secrets-we-bury",
        "imdb": "6.6",
        "year": "2025",
        "image": "https://img.fullhdfilmizlesene.live/poster/film/the-secrets-we-bury-90403.jpg",
        "rapid_link": "https://rapidvid.net/vod/v1x770f87fe"
    },
    {
        "title": "Soul on Fire",
        "link": "https://www.fullhdfilmizlesene.live/film/soul-on-fire-2",
        "imdb": "6.4",
        "year": "2025",
        "image": "https://img.fullhdfilmizlesene.live/poster/film/soul-on-fire-2-5585.jpg",
        "rapid_link": "https://rapidvid.net/vod/v1xe1db1b59"
    },
    {
        "title": "Aaryan",
        "link": "https://www.fullhdfilmizlesene.live/film/aaryan",
        "imdb": "6.3",
        "year": "2025",
        "image": "https://img.fullhdfilmizlesene.live/poster/film/aaryan-96873.jpg",
        "rapid_link": "https://rapidvid.net/vod/v1xf9b4c5c5"
    },
    {
        "title": "Siyah Telefon 2",
        "link": "https://www.fullhdfilmizlesene.live/film/siyah-telefon-2",
        "imdb": "6.6",
        "year": "2025",
        "image": "https://img.fullhdfilmizlesene.live/poster/film/siyah-telefon-2-black-phone-2-7852.jpg",
        "rapid_link": "https://rapidvid.net/vod/v1x80fc6ca4"
    },
    {
        "title": "Siyah Telefon",
        "link": "https://www.fullhdfilmizlesene.live/film/siyah-telefon",
        "imdb": "6.9",
        "year": "2021",
        "image": "https://img.fullhdfilmizlesene.live/poster/film/siyah-telefon-the-black-phone-97442.jpg",
        "rapid_link": "https://rapidvid.net/vod/v1xebc860b3"
    },
    {
        "title": "Bıçaklar Çekildi: Ölü Adamın Uyanışı",
        "link": "https://www.fullhdfilmizlesene.live/film/bicaklar-cekildi-olu-adamin-uyanisi",
        "imdb": "7.9",
        "year": "2025",
        "image": "https://img.fullhdfilmizlesene.live/poster/film/bicaklar-cekildi-olu-adamin-uyanisi-wake-up-dead-man-1689.jpg",
        "rapid_link": "https://rapidvid.net/vod/v1x9d7dfcf8"
    },
    {
        "title": "Bıçaklar Çekildi: Gizemli Bir Serüven",
        "link": "https://www.fullhdfilmizlesene.live/film/bicaklar-cekildi-gizemli-bir-seruven",
        "imdb": "7.1",
        "year": "2022",
        "image": "https://img.fullhdfilmizlesene.live/poster/film/bicaklar-cekildi-gizemli-bir-seruven-38908.jpg",
        "rapid_link": "https://rapidvid.net/vod/v1x21075ca0"
    },
    {
        "title": "Bıçaklar Çekildi",
        "link": "https://www.fullhdfilmizlesene.live/film/bicaklar-cekildi",
        "imdb": "7.9",
        "year": "2019",
        "image": "https://img.fullhdfilmizlesene.live/poster/film/fullhd-knivesout2019-izle.jpg",
        "rapid_link": "https://rapidvid.net/vod/v1xdb15d50e"
    },
    {
        "title": "Merv",
        "link": "https://www.fullhdfilmizlesene.live/film/merv",
        "imdb": "5.6",
        "year": "2025",
        "image": "https://img.fullhdfilmizlesene.live/poster/film/merv-8666.jpg",
        "rapid_link": "https://rapidvid.net/vod/v1x6cc386c8"
    },
    {
        "title": "The Prosecutor",
        "link": "https://www.fullhdfilmizlesene.live/film/the-prosecutor",
        "imdb": "6.7",
        "year": "2024",
        "image": "https://img.fullhdfilmizlesene.live/poster/film/fullhd-the-prosecutor-ng-poon.jpg",
        "rapid_link": "https://rapidvid.net/vod/v1x4267c9e6"
    },
    {
        "title": "Sunny Sanskari ve Tulsi Kumari",
        "link": "https://www.fullhdfilmizlesene.live/film/sunny-sanskari-ve-tulsi-kumari",
        "imdb": "5.5",
        "year": "2025",
        "image": "https://img.fullhdfilmizlesene.live/poster/film/sunny-sanskari-ve-tulsi-kumari-99528.jpg",
        "rapid_link": "https://rapidvid.net/vod/v1x0390ff09"
    },
    {
        "title": "Köln 75",
        "link": "https://www.fullhdfilmizlesene.live/film/koln-75",
        "imdb": "7.2",
        "year": "2025",
        "image": "https://img.fullhdfilmizlesene.live/poster/film/koln-75-14833.jpg",
        "rapid_link": "https://rapidvid.net/vod/v1x6f2d9197"
    },
    {
        "title": "Aİ",
        "link": "https://www.fullhdfilmizlesene.live/film/ai-2022",
        "imdb": "6.7",
        "year": "2022",
        "image": "https://img.fullhdfilmizlesene.live/poster/film/ai-eo-35904.jpg",
        "rapid_link": "https://rapidvid.net/vod/v1xbd7e50f6"
    },
    {
        "title": "Kendimi Kaybettim",
        "link": "https://www.fullhdfilmizlesene.live/film/kendimi-kaybettim",
        "imdb": "8.1",
        "year": "2025",
        "image": "https://img.fullhdfilmizlesene.live/poster/film/kendimi-kaybettim-lupa-daratan-43590.jpg",
        "rapid_link": "https://rapidvid.net/vod/v1x71c2c16a"
    },
    {
        "title": "Hurry Up Tomorrow",
        "link": "https://www.fullhdfilmizlesene.live/film/hurry-up-tomorrow-2",
        "imdb": "5.3",
        "year": "2025",
        "image": "https://img.fullhdfilmizlesene.live/poster/film/hurry-up-tomorrow-2-40607.jpg",
        "rapid_link": "https://rapidvid.net/vod/v1x2778e535"
    },
    {
        "title": "Avatar Ateş ve Kül",
        "link": "https://www.fullhdfilmizlesene.live/film/avatar-ates-ve-kul-1",
        "imdb": "0",
        "year": "2025",
        "image": "https://img.fullhdfilmizlesene.live/poster/film/avatar-ates-ve-kul-avatar-fire-and-ash-57128.jpg",
        "rapid_link": "https://rapidvid.net/vod/v1x5cb0c5d4"
    }
]