[
    {
        "title": "Lanetli Göl",
        "link": "https://www.fullhdfilmizlesene.live/film/lanetli-gol",
        "imdb": "4.7",
        "year": "2022",
        "image": "https://img.fullhdfilmizlesene.live/poster/film/monstrous-29422.jpg"
    },
    {
        "title": "OMG 2",
        "link": "https://www.fullhdfilmizlesene.live/film/omg-2",
        "imdb": "7.6",
        "year": "2023",
        "image": "https://img.fullhdfilmizlesene.live/poster/film/omg-2-97944.jpg"
    },
    {
        "title": "7 Churches",
        "link": "https://www.fullhdfilmizlesene.live/film/7-churches",
        "imdb": "3.8",
        "year": "2022",
        "image": "https://img.fullhdfilmizlesene.live/poster/film/7-churches-2997.jpg"
    },
    {
        "title": "Suikastçı Kulübü",
        "link": "https://www.fullhdfilmizlesene.live/film/suikastci-kulubu",
        "imdb": "4.7",
        "year": "2023",
        "image": "https://img.fullhdfilmizlesene.live/poster/film/suikastci-kulubu-assassin-club-10864.jpg"
    },
    {
        "title": "Zodyak Şövalyeleri",
        "link": "https://www.fullhdfilmizlesene.live/film/zodyak-sovalyeleri",
        "imdb": "4.4",
        "year": "2023",
        "image": "https://img.fullhdfilmizlesene.live/poster/film/knights-of-the-zodiac-fhd-80366.jpg"
    },
    {
        "title": "Gecenin Kurbanı",
        "link": "https://www.fullhdfilmizlesene.live/film/gecenin-kurbani",
        "imdb": "4.2",
        "year": "2021",
        "image": "https://img.fullhdfilmizlesene.live/poster/film/take-back-the-night-6242.jpg"
    },
    {
        "title": "Geçmişe Sünger",
        "link": "https://www.fullhdfilmizlesene.live/film/gecmise-sunger",
        "imdb": "5.9",
        "year": "2022",
        "image": "https://img.fullhdfilmizlesene.live/poster/film/moving-on-51164.jpg"
    },
    {
        "title": "Armageddon Time",
        "link": "https://www.fullhdfilmizlesene.live/film/armageddon-time",
        "imdb": "6.5",
        "year": "2022",
        "image": "https://img.fullhdfilmizlesene.live/poster/film/armageddon-time-1743.jpg"
    },
    {
        "title": "Scarlett Cross: Agents of D.E.A.T.H.",
        "link": "https://www.fullhdfilmizlesene.live/film/scarlett-cross-agents-of-d-e-a-t-h",
        "imdb": "5.0",
        "year": "2022",
        "image": "https://img.fullhdfilmizlesene.live/poster/film/scarlett-cross-agents-of-death-74941.jpg"
    },
    {
        "title": "Nian Shou",
        "link": "https://www.fullhdfilmizlesene.live/film/nian-shou",
        "imdb": "4.6",
        "year": "2020",
        "image": "https://img.fullhdfilmizlesene.live/poster/film/nian-shou-8986.jpg"
    },
    {
        "title": "Mojave Diamonds",
        "link": "https://www.fullhdfilmizlesene.live/film/mojave-diamonds",
        "imdb": "2.9",
        "year": "2023",
        "image": "https://img.fullhdfilmizlesene.live/poster/film/mojave-diamonds-42828.jpg"
    },
    {
        "title": "The Mask of Shura of Fire Cloud",
        "link": "https://www.fullhdfilmizlesene.live/film/the-mask-of-shura-of-fire-cloud",
        "imdb": "5.6",
        "year": "2020",
        "image": "https://img.fullhdfilmizlesene.live/poster/film/the-mask-of-shura-of-fire-cloud-17347.jpg"
    },
    {
        "title": "Made for Each Other",
        "link": "https://www.fullhdfilmizlesene.live/film/made-for-each-other",
        "imdb": "5.9",
        "year": "2023",
        "image": "https://img.fullhdfilmizlesene.live/poster/film/made-for-each-other-54301.jpg"
    },
    {
        "title": "Unutulmaz Bir Yıl: Yaz",
        "link": "https://www.fullhdfilmizlesene.live/film/unutulmaz-bir-yil-yaz",
        "imdb": "5.3",
        "year": "2023",
        "image": "https://img.fullhdfilmizlesene.live/poster/film/unutulmaz-bir-yil-yaz-42927.jpg"
    },
    {
        "title": "Mevsimler",
        "link": "https://www.fullhdfilmizlesene.live/film/mevsimler-2",
        "imdb": "5.1",
        "year": "2023",
        "image": "https://img.fullhdfilmizlesene.live/poster/film/mevsimler-seasons-16309.jpg"
    },
    {
        "title": "Lamborghini: Efsanenin Ardındaki Adam",
        "link": "https://www.fullhdfilmizlesene.live/film/lamborghini-efsanenin-ardindaki-adam",
        "imdb": "5.4",
        "year": "2022",
        "image": "https://img.fullhdfilmizlesene.live/poster/film/lamborghini-efsanenin-ardindaki-adam-the-man-behind-the-legend-24483.jpg"
    },
    {
        "title": "Munster Ailesi",
        "link": "https://www.fullhdfilmizlesene.live/film/munster-ailesi",
        "imdb": "4.5",
        "year": "2022",
        "image": "https://img.fullhdfilmizlesene.live/poster/film/the-munsters-34010.jpg"
    },
    {
        "title": "Gençlik Ateşi: Ya Amigoluk Ya Ölüm",
        "link": "https://www.fullhdfilmizlesene.live/film/genclik-atesi-ya-amigoluk-ya-olum",
        "imdb": "3.7",
        "year": "2022",
        "image": "https://img.fullhdfilmizlesene.live/poster/film/genclik-atesi-ya-amigoluk-ya-olum-bring-it-on-cheer-or-die-90934.jpg"
    }
]